testcanarybot/__init__.py
testcanarybot/__main__.py
testcanarybot/enums.py
testcanarybot/exceptions.py
testcanarybot/keyboard.py
testcanarybot/packaet.py
testcanarybot/uploader.py
testcanarybot/framework/__init__.py
testcanarybot/framework/_api.py
testcanarybot/framework/_application.py
testcanarybot/framework/_library.py
testcanarybot/framework/_threading.py
testcanarybot/framework/_values.py
testcanarybot/objects/__init__.py
testcanarybot/objects/data.py
testcanarybot/objects/decorators.py
testcanarybot/objects/tools.py
testcanarybot-1.1.3.dist-info/LICENSE
testcanarybot-1.1.3.dist-info/METADATA
testcanarybot-1.1.3.dist-info/WHEEL
testcanarybot-1.1.3.dist-info/top_level.txt
testcanarybot-1.1.3.dist-info/RECORD
