Metadata-Version: 2.1
Name: testcanarybot
Version: 1.1.3
Summary: asynchronous VK Bot Framework
Home-page: https://github.com/kensoi/testcanarybot/
Author: andprokofieff
Author-email: prokofieff@internet.ru
License: UNKNOWN
Platform: UNKNOWN
Classifier: Programming Language :: Python :: 3
Classifier: License :: OSI Approved :: MIT License
Classifier: Operating System :: OS Independent
Requires-Python: >=3.7
Requires-Dist: aiohttp
Requires-Dist: six
